infer_gender/__init__.py
infer_gender/predict.py
infer_gender/data/.DS_Store
infer_gender/data/model.h5
infer_gender/data/tokenizer.pickle
infer_gender/data/py37/tokenizer.pickle
tests/__init__.py
tests/main.py
infer_gender-0.2.0.2.dist-info/LICENSE
infer_gender-0.2.0.2.dist-info/METADATA
infer_gender-0.2.0.2.dist-info/WHEEL
infer_gender-0.2.0.2.dist-info/top_level.txt
infer_gender-0.2.0.2.dist-info/RECORD
