Metadata-Version: 2.1
Name: infer-gender
Version: 0.2.0.2
Summary: Infer gender from the Indian first name or full name
Home-page: https://github.com/bnriiitb/infer-gender
Author: Nagaraju Budigam
Author-email: nagaraju.iith@gmail.com
License: MIT
Platform: UNKNOWN
Classifier: License :: OSI Approved :: MIT License
Classifier: Programming Language :: Python :: 3
Classifier: Programming Language :: Python :: 3.7
Classifier: Programming Language :: Python :: 3.8
Requires-Dist: scikit-learn (>0.22)
Requires-Dist: tensorflow (>2.3.0)
